ykman/__init__.py
ykman/_cli/__init__.py
ykman/_cli/__main__.py
ykman/_cli/apdu.py
ykman/_cli/config.py
ykman/_cli/fido.py
ykman/_cli/hsmauth.py
ykman/_cli/info.py
ykman/_cli/oath.py
ykman/_cli/openpgp.py
ykman/_cli/otp.py
ykman/_cli/piv.py
ykman/_cli/script.py
ykman/_cli/securitydomain.py
ykman/_cli/util.py
ykman/base.py
ykman/device.py
ykman/diagnostics.py
ykman/fido.py
ykman/hid/__init__.py
ykman/hid/base.py
ykman/hid/fido.py
ykman/hid/freebsd.py
ykman/hid/linux.py
ykman/hid/macos.py
ykman/hid/windows.py
ykman/hsmauth.py
ykman/logging.py
ykman/logging_setup.py
ykman/oath.py
ykman/openpgp.py
ykman/otp.py
ykman/pcsc/__init__.py
ykman/piv.py
ykman/py.typed
ykman/scancodes/__init__.py
ykman/scancodes/bepo.py
ykman/scancodes/de.py
ykman/scancodes/fr.py
ykman/scancodes/it.py
ykman/scancodes/modhex.py
ykman/scancodes/norman.py
ykman/scancodes/uk.py
ykman/scancodes/us.py
ykman/scripting.py
ykman/settings.py
ykman/util.py
yubikit/__init__.py
yubikit/core/__init__.py
yubikit/core/fido.py
yubikit/core/otp.py
yubikit/core/smartcard/__init__.py
yubikit/core/smartcard/scp.py
yubikit/hsmauth.py
yubikit/logging.py
yubikit/management.py
yubikit/oath.py
yubikit/openpgp.py
yubikit/piv.py
yubikit/py.typed
yubikit/securitydomain.py
yubikit/support.py
yubikit/yubiotp.py
yubikey_manager-5.8.0.dist-info/COPYING
yubikey_manager-5.8.0.dist-info/METADATA
yubikey_manager-5.8.0.dist-info/WHEEL
yubikey_manager-5.8.0.dist-info/entry_points.txt
yubikey_manager-5.8.0.dist-info/RECORD
